dash_react_syntax_highlighter/DashReactSyntaxHighlighter.py
dash_react_syntax_highlighter/__init__.py
dash_react_syntax_highlighter/_imports_.py
dash_react_syntax_highlighter/dash_react_syntax_highlighter.min.js
dash_react_syntax_highlighter/dash_react_syntax_highlighter.min.js.map
dash_react_syntax_highlighter/metadata.json
dash_react_syntax_highlighter/package-info.json
dash_react_syntax_highlighter-0.0.2.dist-info/LICENSE
dash_react_syntax_highlighter-0.0.2.dist-info/METADATA
dash_react_syntax_highlighter-0.0.2.dist-info/WHEEL
dash_react_syntax_highlighter-0.0.2.dist-info/top_level.txt
dash_react_syntax_highlighter-0.0.2.dist-info/RECORD
